[{"mCalorie":0.0,"mDistance":0.0,"mNowHealthyStep":0,"mRunStepCount":0,"mSpeed":0.0,"mStartTime":1711249200000,"mStepCount":0,"mTimeUnit":600000,"mTotalActiveTime":0.0,"mWalkStepCount":0},{"mCalorie":0.0,"mDistance":0.0,"mNowHealthyStep":0,"mRunStepCount":0,"mSpeed":0.0,"mStartTime":1711249800000,"mStepCount":0,"mTimeUnit":600000,"mTotalActiveTime":0.0,"mWalkStepCount":0},{"mCalorie":0.0,"mDistance":0.0,"mNowHealthyStep":0,"mRunStepCount":0,"mSpeed":0.0,"mStartTime":1711250400000,"mStepCount":0,"mTimeUnit":600000,"mTotalActiveTime":0.0,"mWalkStepCount":0},{"mCalorie":0.0,"mDistance":0.0,"mNowHealthyStep":0,"mRunStepCount":0,"mSpeed":0.0,"mStartTime":1711251000000,"mStepCount":0,"mTimeUnit":600000,"mTotalActiveTime":0.0,"mWalkStepCount":0},{"mCalorie":0.0,"mDistance":0.0,"mNowHealthyStep":0,"mRunStepCount":0,"mSpeed":0.0,"mStartTime":1711251600000,"mStepCount":0,"mTimeUnit":600000,"mTotalActiveTime":0.0,"mWalkStepCount":0},{"mCalorie":0.0,"mDistance":0.0,"mNowHealthyStep":0,"mRunStepCount":0,"mSpeed":0.0,"mStartTime":1711252200000,"mStepCount":0,"mTimeUnit":600000,"mTotalActiveTime":0.0,"mWalkStepCount":0},{"mCalorie":0.0,"mDistance":0.0,"mNowHealthyStep":0,"mRunStepCount":0,"mSpeed":0.0,"mStartTime":1711252800000,"mStepCount":0,"mTimeUnit":600000,"mTotalActiveTime":0.0,"mWalkStepCount":0},{"mCalorie":0.0,"mDistance":0.0,"mNowHealthyStep":0,"mRunStepCount":0,"mSpeed":0.0,"mStartTime":1711253400000,"mStepCount":0,"mTimeUnit":600000,"mTotalActiveTime":0.0,"mWalkStepCount":0},{"mCalorie":0.0,"mDistance":0.0,"mNowHealthyStep":0,"mRunStepCount":0,"mSpeed":0.0,"mStartTime":1711254000000,"mStepCount":0,"mTimeUnit":600000,"mTotalActiveTime":0.0,"mWalkStepCount":0},{"mCalorie":0.0,"mDistance":0.0,"mNowHealthyStep":0,"mRunStepCount":0,"mSpeed":0.0,"mStartTime":1711254600000,"mStepCount":0,"mTimeUnit":600000,"mTotalActiveTime":0.0,"mWalkStepCount":0},{"mCalorie":0.0,"mDistance":0.0,"mNowHealthyStep":0,"mRunStepCount":0,"mSpeed":0.0,"mStartTime":1711255200000,"mStepCount":0,"mTimeUnit":600000,"mTotalActiveTime":0.0,"mWalkStepCount":0},{"mCalorie":0.0,"mDistance":0.0,"mNowHealthyStep":0,"mRunStepCount":0,"mSpeed":0.0,"mStartTime":1711255800000,"mStepCount":0,"mTimeUnit":600000,"mTotalActiveTime":0.0,"mWalkStepCount":0},{"mCalorie":0.0,"mDistance":0.0,"mNowHealthyStep":0,"mRunStepCount":0,"mSpeed":0.0,"mStartTime":1711256400000,"mStepCount":0,"mTimeUnit":600000,"mTotalActiveTime":0.0,"mWalkStepCount":0},{"mCalorie":0.0,"mDistance":0.0,"mNowHealthyStep":0,"mRunStepCount":0,"mSpeed":0.0,"mStartTime":1711257000000,"mStepCount":0,"mTimeUnit":600000,"mTotalActiveTime":0.0,"mWalkStepCount":0},{"mCalorie":0.0,"mDistance":0.0,"mNowHealthyStep":0,"mRunStepCount":0,"mSpeed":0.0,"mStartTime":1711257600000,"mStepCount":0,"mTimeUnit":600000,"mTotalActiveTime":0.0,"mWalkStepCount":0},{"mCalorie":0.0,"mDistance":0.0,"mNowHealthyStep":0,"mRunStepCount":0,"mSpeed":0.0,"mStartTime":1711258200000,"mStepCount":0,"mTimeUnit":600000,"mTotalActiveTime":0.0,"mWalkStepCount":0},{"mCalorie":0.0,"mDistance":0.0,"mNowHealthyStep":0,"mRunStepCount":0,"mSpeed":0.0,"mStartTime":1711258800000,"mStepCount":0,"mTimeUnit":600000,"mTotalActiveTime":0.0,"mWalkStepCount":0},{"mCalorie":0.0,"mDistance":0.0,"mNowHealthyStep":0,"mRunStepCount":0,"mSpeed":0.0,"mStartTime":1711259400000,"mStepCount":0,"mTimeUnit":600000,"mTotalActiveTime":0.0,"mWalkStepCount":0},{"mCalorie":0.0,"mDistance":0.0,"mNowHealthyStep":0,"mRunStepCount":0,"mSpeed":0.0,"mStartTime":1711260000000,"mStepCount":0,"mTimeUnit":600000,"mTotalActiveTime":0.0,"mWalkStepCount":0},{"mCalorie":0.0,"mDistance":0.0,"mNowHealthyStep":0,"mRunStepCount":0,"mSpeed":0.0,"mStartTime":1711260600000,"mStepCount":0,"mTimeUnit":600000,"mTotalActiveTime":0.0,"mWalkStepCount":0},{"mCalorie":0.0,"mDistance":0.0,"mNowHealthyStep":0,"mRunStepCount":0,"mSpeed":0.0,"mStartTime":1711261200000,"mStepCount":0,"mTimeUnit":600000,"mTotalActiveTime":0.0,"mWalkStepCount":0},{"mCalorie":0.0,"mDistance":0.0,"mNowHealthyStep":0,"mRunStepCount":0,"mSpeed":0.0,"mStartTime":1711261800000,"mStepCount":0,"mTimeUnit":600000,"mTotalActiveTime":0.0,"mWalkStepCount":0},{"mCalorie":0.0,"mDistance":0.0,"mNowHealthyStep":0,"mRunStepCount":0,"mSpeed":0.0,"mStartTime":1711262400000,"mStepCount":0,"mTimeUnit":600000,"mTotalActiveTime":0.0,"mWalkStepCount":0},{"mCalorie":0.0,"mDistance":0.0,"mNowHealthyStep":0,"mRunStepCount":0,"mSpeed":0.0,"mStartTime":1711263000000,"mStepCount":0,"mTimeUnit":600000,"mTotalActiveTime":0.0,"mWalkStepCount":0},{"mCalorie":0.0,"mDistance":0.0,"mNowHealthyStep":0,"mRunStepCount":0,"mSpeed":0.0,"mStartTime":1711263600000,"mStepCount":0,"mTimeUnit":600000,"mTotalActiveTime":0.0,"mWalkStepCount":0},{"mCalorie":0.0,"mDistance":0.0,"mNowHealthyStep":0,"mRunStepCount":0,"mSpeed":0.0,"mStartTime":1711264200000,"mStepCount":0,"mTimeUnit":600000,"mTotalActiveTime":0.0,"mWalkStepCount":0},{"mCalorie":0.0,"mDistance":0.0,"mNowHealthyStep":0,"mRunStepCount":0,"mSpeed":0.0,"mStartTime":1711264800000,"mStepCount":0,"mTimeUnit":600000,"mTotalActiveTime":0.0,"mWalkStepCount":0},{"mCalorie":0.0,"mDistance":0.0,"mNowHealthyStep":0,"mRunStepCount":0,"mSpeed":0.0,"mStartTime":1711265400000,"mStepCount":0,"mTimeUnit":600000,"mTotalActiveTime":0.0,"mWalkStepCount":0},{"mCalorie":0.0,"mDistance":0.0,"mNowHealthyStep":0,"mRunStepCount":0,"mSpeed":0.0,"mStartTime":1711266000000,"mStepCount":0,"mTimeUnit":600000,"mTotalActiveTime":0.0,"mWalkStepCount":0},{"mCalorie":0.0,"mDistance":0.0,"mNowHealthyStep":0,"mRunStepCount":0,"mSpeed":0.0,"mStartTime":1711266600000,"mStepCount":0,"mTimeUnit":600000,"mTotalActiveTime":0.0,"mWalkStepCount":0},{"mCalorie":0.0,"mDistance":0.0,"mNowHealthyStep":0,"mRunStepCount":0,"mSpeed":0.0,"mStartTime":1711267200000,"mStepCount":0,"mTimeUnit":600000,"mTotalActiveTime":0.0,"mWalkStepCount":0},{"mCalorie":0.0,"mDistance":0.0,"mNowHealthyStep":0,"mRunStepCount":0,"mSpeed":0.0,"mStartTime":1711267800000,"mStepCount":0,"mTimeUnit":600000,"mTotalActiveTime":0.0,"mWalkStepCount":0},{"mCalorie":0.0,"mDistance":0.0,"mNowHealthyStep":0,"mRunStepCount":0,"mSpeed":0.0,"mStartTime":1711268400000,"mStepCount":0,"mTimeUnit":600000,"mTotalActiveTime":0.0,"mWalkStepCount":0},{"mCalorie":0.0,"mDistance":0.0,"mNowHealthyStep":0,"mRunStepCount":0,"mSpeed":0.0,"mStartTime":1711269000000,"mStepCount":0,"mTimeUnit":600000,"mTotalActiveTime":0.0,"mWalkStepCount":0},{"mCalorie":0.0,"mDistance":0.0,"mNowHealthyStep":0,"mRunStepCount":0,"mSpeed":0.0,"mStartTime":1711269600000,"mStepCount":0,"mTimeUnit":600000,"mTotalActiveTime":0.0,"mWalkStepCount":0},{"mCalorie":0.0,"mDistance":0.0,"mNowHealthyStep":0,"mRunStepCount":0,"mSpeed":0.0,"mStartTime":1711270200000,"mStepCount":0,"mTimeUnit":600000,"mTotalActiveTime":0.0,"mWalkStepCount":0},{"mCalorie":0.0,"mDistance":0.0,"mNowHealthyStep":0,"mRunStepCount":0,"mSpeed":0.0,"mStartTime":1711270800000,"mStepCount":0,"mTimeUnit":600000,"mTotalActiveTime":0.0,"mWalkStepCount":0},{"mCalorie":0.0,"mDistance":0.0,"mNowHealthyStep":0,"mRunStepCount":0,"mSpeed":0.0,"mStartTime":1711271400000,"mStepCount":0,"mTimeUnit":600000,"mTotalActiveTime":0.0,"mWalkStepCount":0},{"mCalorie":0.0,"mDistance":0.0,"mNowHealthyStep":0,"mRunStepCount":0,"mSpeed":0.0,"mStartTime":1711272000000,"mStepCount":0,"mTimeUnit":600000,"mTotalActiveTime":0.0,"mWalkStepCount":0},{"mCalorie":0.0,"mDistance":0.0,"mNowHealthyStep":0,"mRunStepCount":0,"mSpeed":0.0,"mStartTime":1711272600000,"mStepCount":0,"mTimeUnit":600000,"mTotalActiveTime":0.0,"mWalkStepCount":0},{"mCalorie":0.0,"mDistance":0.0,"mNowHealthyStep":0,"mRunStepCount":0,"mSpeed":0.0,"mStartTime":1711273200000,"mStepCount":0,"mTimeUnit":600000,"mTotalActiveTime":0.0,"mWalkStepCount":0},{"mCalorie":0.0,"mDistance":0.0,"mNowHealthyStep":0,"mRunStepCount":0,"mSpeed":0.0,"mStartTime":1711273800000,"mStepCount":0,"mTimeUnit":600000,"mTotalActiveTime":0.0,"mWalkStepCount":0},{"mCalorie":0.0,"mDistance":0.0,"mNowHealthyStep":0,"mRunStepCount":0,"mSpeed":0.0,"mStartTime":1711274400000,"mStepCount":0,"mTimeUnit":600000,"mTotalActiveTime":0.0,"mWalkStepCount":0},{"mCalorie":0.0,"mDistance":0.0,"mNowHealthyStep":0,"mRunStepCount":0,"mSpeed":0.0,"mStartTime":1711275000000,"mStepCount":0,"mTimeUnit":600000,"mTotalActiveTime":0.0,"mWalkStepCount":0},{"mCalorie":0.0,"mDistance":0.0,"mNowHealthyStep":0,"mRunStepCount":0,"mSpeed":0.0,"mStartTime":1711275600000,"mStepCount":0,"mTimeUnit":600000,"mTotalActiveTime":0.0,"mWalkStepCount":0},{"mCalorie":0.0,"mDistance":0.0,"mNowHealthyStep":0,"mRunStepCount":0,"mSpeed":0.0,"mStartTime":1711276200000,"mStepCount":0,"mTimeUnit":600000,"mTotalActiveTime":0.0,"mWalkStepCount":0},{"mCalorie":0.0,"mDistance":0.0,"mNowHealthyStep":0,"mRunStepCount":0,"mSpeed":0.0,"mStartTime":1711276800000,"mStepCount":0,"mTimeUnit":600000,"mTotalActiveTime":0.0,"mWalkStepCount":0},{"mCalorie":0.0,"mDistance":0.0,"mNowHealthyStep":0,"mRunStepCount":0,"mSpeed":0.0,"mStartTime":1711277400000,"mStepCount":0,"mTimeUnit":600000,"mTotalActiveTime":0.0,"mWalkStepCount":0},{"mCalorie":0.0,"mDistance":0.0,"mNowHealthyStep":0,"mRunStepCount":0,"mSpeed":0.0,"mStartTime":1711278000000,"mStepCount":0,"mTimeUnit":600000,"mTotalActiveTime":0.0,"mWalkStepCount":0},{"mCalorie":0.0,"mDistance":0.0,"mNowHealthyStep":0,"mRunStepCount":0,"mSpeed":0.0,"mStartTime":1711278600000,"mStepCount":0,"mTimeUnit":600000,"mTotalActiveTime":0.0,"mWalkStepCount":0},{"mCalorie":0.0,"mDistance":0.0,"mNowHealthyStep":0,"mRunStepCount":0,"mSpeed":0.0,"mStartTime":1711279200000,"mStepCount":0,"mTimeUnit":600000,"mTotalActiveTime":0.0,"mWalkStepCount":0},{"mCalorie":0.0,"mDistance":0.0,"mNowHealthyStep":0,"mRunStepCount":0,"mSpeed":0.0,"mStartTime":1711279800000,"mStepCount":0,"mTimeUnit":600000,"mTotalActiveTime":0.0,"mWalkStepCount":0},{"mCalorie":0.0,"mDistance":0.0,"mNowHealthyStep":0,"mRunStepCount":0,"mSpeed":0.0,"mStartTime":1711280400000,"mStepCount":0,"mTimeUnit":600000,"mTotalActiveTime":0.0,"mWalkStepCount":0},{"mCalorie":0.0,"mDistance":0.0,"mNowHealthyStep":0,"mRunStepCount":0,"mSpeed":0.0,"mStartTime":1711281000000,"mStepCount":0,"mTimeUnit":600000,"mTotalActiveTime":0.0,"mWalkStepCount":0},{"mCalorie":0.0,"mDistance":0.0,"mNowHealthyStep":0,"mRunStepCount":0,"mSpeed":0.0,"mStartTime":1711281600000,"mStepCount":0,"mTimeUnit":600000,"mTotalActiveTime":0.0,"mWalkStepCount":0},{"mCalorie":0.0,"mDistance":0.0,"mNowHealthyStep":0,"mRunStepCount":0,"mSpeed":0.0,"mStartTime":1711282200000,"mStepCount":0,"mTimeUnit":600000,"mTotalActiveTime":0.0,"mWalkStepCount":0},{"mCalorie":0.0,"mDistance":0.0,"mNowHealthyStep":0,"mRunStepCount":0,"mSpeed":0.0,"mStartTime":1711282800000,"mStepCount":0,"mTimeUnit":600000,"mTotalActiveTime":0.0,"mWalkStepCount":0},{"mCalorie":0.0,"mDistance":0.0,"mNowHealthyStep":0,"mRunStepCount":0,"mSpeed":0.0,"mStartTime":1711283400000,"mStepCount":0,"mTimeUnit":600000,"mTotalActiveTime":0.0,"mWalkStepCount":0},{"mCalorie":16.177991860000002,"mDistance":246.90054800000001,"mNowHealthyStep":0,"mRunStepCount":27,"mSpeed":5.659138202667236,"mStartTime":1711284000000,"mStepCount":303,"mTimeUnit":600000,"mTotalActiveTime":157063.1309015312,"mWalkStepCount":276},{"mCalorie":28.6457537,"mDistance":456.894261,"mNowHealthyStep":0,"mRunStepCount":3,"mSpeed":5.471199035644531,"mStartTime":1711284600000,"mStepCount":570,"mTimeUnit":600000,"mTotalActiveTime":300632.3422527997,"mWalkStepCount":567},{"mCalorie":19.4489212,"mDistance":303.9953625,"mNowHealthyStep":0,"mRunStepCount":0,"mSpeed":4.989291191101074,"mStartTime":1711285200000,"mStepCount":380,"mTimeUnit":600000,"mTotalActiveTime":219346.4585659777,"mWalkStepCount":380},{"mCalorie":21.362663429999998,"mDistance":319.81237999999996,"mNowHealthyStep":0,"mRunStepCount":30,"mSpeed":5.696110248565674,"mStartTime":1711285800000,"mStepCount":387,"mTimeUnit":600000,"mTotalActiveTime":202124.69935324718,"mWalkStepCount":357},{"mCalorie":20.0056152,"mDistance":300.81298899999996,"mNowHealthyStep":0,"mRunStepCount":23,"mSpeed":5.536763668060303,"mStartTime":1711286400000,"mStepCount":367,"mTimeUnit":600000,"mTotalActiveTime":195588.4055276118,"mWalkStepCount":344},{"mCalorie":2.7694626,"mDistance":40.901978,"mNowHealthyStep":0,"mRunStepCount":0,"mSpeed":4.784430027008057,"mStartTime":1711287000000,"mStepCount":50,"mTimeUnit":600000,"mTotalActiveTime":30776.313995354005,"mWalkStepCount":50},{"mCalorie":0.0,"mDistance":0.0,"mNowHealthyStep":0,"mRunStepCount":0,"mSpeed":0.0,"mStartTime":1711287600000,"mStepCount":0,"mTimeUnit":600000,"mTotalActiveTime":0.0,"mWalkStepCount":0},{"mCalorie":0.0,"mDistance":0.0,"mNowHealthyStep":0,"mRunStepCount":0,"mSpeed":0.0,"mStartTime":1711288200000,"mStepCount":0,"mTimeUnit":600000,"mTotalActiveTime":0.0,"mWalkStepCount":0},{"mCalorie":0.0,"mDistance":0.0,"mNowHealthyStep":0,"mRunStepCount":0,"mSpeed":0.0,"mStartTime":1711288800000,"mStepCount":0,"mTimeUnit":600000,"mTotalActiveTime":0.0,"mWalkStepCount":0},{"mCalorie":0.0,"mDistance":0.0,"mNowHealthyStep":0,"mRunStepCount":0,"mSpeed":0.0,"mStartTime":1711289400000,"mStepCount":0,"mTimeUnit":600000,"mTotalActiveTime":0.0,"mWalkStepCount":0},{"mCalorie":0.0,"mDistance":0.0,"mNowHealthyStep":0,"mRunStepCount":0,"mSpeed":0.0,"mStartTime":1711290000000,"mStepCount":0,"mTimeUnit":600000,"mTotalActiveTime":0.0,"mWalkStepCount":0},{"mCalorie":0.0,"mDistance":0.0,"mNowHealthyStep":0,"mRunStepCount":0,"mSpeed":0.0,"mStartTime":1711290600000,"mStepCount":0,"mTimeUnit":600000,"mTotalActiveTime":0.0,"mWalkStepCount":0},{"mCalorie":0.0,"mDistance":0.0,"mNowHealthyStep":0,"mRunStepCount":0,"mSpeed":0.0,"mStartTime":1711291200000,"mStepCount":0,"mTimeUnit":600000,"mTotalActiveTime":0.0,"mWalkStepCount":0},{"mCalorie":0.0,"mDistance":0.0,"mNowHealthyStep":0,"mRunStepCount":0,"mSpeed":0.0,"mStartTime":1711291800000,"mStepCount":0,"mTimeUnit":600000,"mTotalActiveTime":0.0,"mWalkStepCount":0},{"mCalorie":0.0,"mDistance":0.0,"mNowHealthyStep":0,"mRunStepCount":0,"mSpeed":0.0,"mStartTime":1711292400000,"mStepCount":0,"mTimeUnit":600000,"mTotalActiveTime":0.0,"mWalkStepCount":0},{"mCalorie":0.0,"mDistance":0.0,"mNowHealthyStep":0,"mRunStepCount":0,"mSpeed":0.0,"mStartTime":1711293000000,"mStepCount":0,"mTimeUnit":600000,"mTotalActiveTime":0.0,"mWalkStepCount":0},{"mCalorie":0.0,"mDistance":0.0,"mNowHealthyStep":0,"mRunStepCount":0,"mSpeed":0.0,"mStartTime":1711293600000,"mStepCount":0,"mTimeUnit":600000,"mTotalActiveTime":0.0,"mWalkStepCount":0},{"mCalorie":0.0,"mDistance":0.0,"mNowHealthyStep":0,"mRunStepCount":0,"mSpeed":0.0,"mStartTime":1711294200000,"mStepCount":0,"mTimeUnit":600000,"mTotalActiveTime":0.0,"mWalkStepCount":0},{"mCalorie":0.0,"mDistance":0.0,"mNowHealthyStep":0,"mRunStepCount":0,"mSpeed":0.0,"mStartTime":1711294800000,"mStepCount":0,"mTimeUnit":600000,"mTotalActiveTime":0.0,"mWalkStepCount":0},{"mCalorie":0.0,"mDistance":0.0,"mNowHealthyStep":0,"mRunStepCount":0,"mSpeed":0.0,"mStartTime":1711295400000,"mStepCount":0,"mTimeUnit":600000,"mTotalActiveTime":0.0,"mWalkStepCount":0},{"mCalorie":0.0,"mDistance":0.0,"mNowHealthyStep":0,"mRunStepCount":0,"mSpeed":0.0,"mStartTime":1711296000000,"mStepCount":0,"mTimeUnit":600000,"mTotalActiveTime":0.0,"mWalkStepCount":0},{"mCalorie":0.0,"mDistance":0.0,"mNowHealthyStep":0,"mRunStepCount":0,"mSpeed":0.0,"mStartTime":1711296600000,"mStepCount":0,"mTimeUnit":600000,"mTotalActiveTime":0.0,"mWalkStepCount":0},{"mCalorie":0.0,"mDistance":0.0,"mNowHealthyStep":0,"mRunStepCount":0,"mSpeed":0.0,"mStartTime":1711297200000,"mStepCount":0,"mTimeUnit":600000,"mTotalActiveTime":0.0,"mWalkStepCount":0},{"mCalorie":0.0,"mDistance":0.0,"mNowHealthyStep":0,"mRunStepCount":0,"mSpeed":0.0,"mStartTime":1711297800000,"mStepCount":0,"mTimeUnit":600000,"mTotalActiveTime":0.0,"mWalkStepCount":0},{"mCalorie":0.0,"mDistance":0.0,"mNowHealthyStep":0,"mRunStepCount":0,"mSpeed":0.0,"mStartTime":1711298400000,"mStepCount":0,"mTimeUnit":600000,"mTotalActiveTime":0.0,"mWalkStepCount":0},{"mCalorie":0.0,"mDistance":0.0,"mNowHealthyStep":0,"mRunStepCount":0,"mSpeed":0.0,"mStartTime":1711299000000,"mStepCount":0,"mTimeUnit":600000,"mTotalActiveTime":0.0,"mWalkStepCount":0},{"mCalorie":0.0,"mDistance":0.0,"mNowHealthyStep":0,"mRunStepCount":0,"mSpeed":0.0,"mStartTime":1711299600000,"mStepCount":0,"mTimeUnit":600000,"mTotalActiveTime":0.0,"mWalkStepCount":0},{"mCalorie":0.0,"mDistance":0.0,"mNowHealthyStep":0,"mRunStepCount":0,"mSpeed":0.0,"mStartTime":1711300200000,"mStepCount":0,"mTimeUnit":600000,"mTotalActiveTime":0.0,"mWalkStepCount":0},{"mCalorie":0.0,"mDistance":0.0,"mNowHealthyStep":0,"mRunStepCount":0,"mSpeed":0.0,"mStartTime":1711300800000,"mStepCount":0,"mTimeUnit":600000,"mTotalActiveTime":0.0,"mWalkStepCount":0},{"mCalorie":0.0,"mDistance":0.0,"mNowHealthyStep":0,"mRunStepCount":0,"mSpeed":0.0,"mStartTime":1711301400000,"mStepCount":0,"mTimeUnit":600000,"mTotalActiveTime":0.0,"mWalkStepCount":0},{"mCalorie":0.0,"mDistance":0.0,"mNowHealthyStep":0,"mRunStepCount":0,"mSpeed":0.0,"mStartTime":1711302000000,"mStepCount":0,"mTimeUnit":600000,"mTotalActiveTime":0.0,"mWalkStepCount":0},{"mCalorie":0.0,"mDistance":0.0,"mNowHealthyStep":0,"mRunStepCount":0,"mSpeed":0.0,"mStartTime":1711302600000,"mStepCount":0,"mTimeUnit":600000,"mTotalActiveTime":0.0,"mWalkStepCount":0},{"mCalorie":0.0,"mDistance":0.0,"mNowHealthyStep":0,"mRunStepCount":0,"mSpeed":0.0,"mStartTime":1711303200000,"mStepCount":0,"mTimeUnit":600000,"mTotalActiveTime":0.0,"mWalkStepCount":0},{"mCalorie":0.0,"mDistance":0.0,"mNowHealthyStep":0,"mRunStepCount":0,"mSpeed":0.0,"mStartTime":1711303800000,"mStepCount":0,"mTimeUnit":600000,"mTotalActiveTime":0.0,"mWalkStepCount":0},{"mCalorie":0.0,"mDistance":0.0,"mNowHealthyStep":0,"mRunStepCount":0,"mSpeed":0.0,"mStartTime":1711304400000,"mStepCount":0,"mTimeUnit":600000,"mTotalActiveTime":0.0,"mWalkStepCount":0},{"mCalorie":0.0,"mDistance":0.0,"mNowHealthyStep":0,"mRunStepCount":0,"mSpeed":0.0,"mStartTime":1711305000000,"mStepCount":0,"mTimeUnit":600000,"mTotalActiveTime":0.0,"mWalkStepCount":0},{"mCalorie":0.0,"mDistance":0.0,"mNowHealthyStep":0,"mRunStepCount":0,"mSpeed":0.0,"mStartTime":1711305600000,"mStepCount":0,"mTimeUnit":600000,"mTotalActiveTime":0.0,"mWalkStepCount":0},{"mCalorie":0.0,"mDistance":0.0,"mNowHealthyStep":0,"mRunStepCount":0,"mSpeed":0.0,"mStartTime":1711306200000,"mStepCount":0,"mTimeUnit":600000,"mTotalActiveTime":0.0,"mWalkStepCount":0},{"mCalorie":0.0,"mDistance":0.0,"mNowHealthyStep":0,"mRunStepCount":0,"mSpeed":0.0,"mStartTime":1711306800000,"mStepCount":0,"mTimeUnit":600000,"mTotalActiveTime":0.0,"mWalkStepCount":0},{"mCalorie":0.0,"mDistance":0.0,"mNowHealthyStep":0,"mRunStepCount":0,"mSpeed":0.0,"mStartTime":1711307400000,"mStepCount":0,"mTimeUnit":600000,"mTotalActiveTime":0.0,"mWalkStepCount":0},{"mCalorie":0.0,"mDistance":0.0,"mNowHealthyStep":0,"mRunStepCount":0,"mSpeed":0.0,"mStartTime":1711308000000,"mStepCount":0,"mTimeUnit":600000,"mTotalActiveTime":0.0,"mWalkStepCount":0},{"mCalorie":0.0,"mDistance":0.0,"mNowHealthyStep":0,"mRunStepCount":0,"mSpeed":0.0,"mStartTime":1711308600000,"mStepCount":0,"mTimeUnit":600000,"mTotalActiveTime":0.0,"mWalkStepCount":0},{"mCalorie":0.0,"mDistance":0.0,"mNowHealthyStep":0,"mRunStepCount":0,"mSpeed":0.0,"mStartTime":1711309200000,"mStepCount":0,"mTimeUnit":600000,"mTotalActiveTime":0.0,"mWalkStepCount":0},{"mCalorie":0.0,"mDistance":0.0,"mNowHealthyStep":0,"mRunStepCount":0,"mSpeed":0.0,"mStartTime":1711309800000,"mStepCount":0,"mTimeUnit":600000,"mTotalActiveTime":0.0,"mWalkStepCount":0},{"mCalorie":0.0,"mDistance":0.0,"mNowHealthyStep":0,"mRunStepCount":0,"mSpeed":0.0,"mStartTime":1711310400000,"mStepCount":0,"mTimeUnit":600000,"mTotalActiveTime":0.0,"mWalkStepCount":0},{"mCalorie":0.0,"mDistance":0.0,"mNowHealthyStep":0,"mRunStepCount":0,"mSpeed":0.0,"mStartTime":1711311000000,"mStepCount":0,"mTimeUnit":600000,"mTotalActiveTime":0.0,"mWalkStepCount":0},{"mCalorie":0.0,"mDistance":0.0,"mNowHealthyStep":0,"mRunStepCount":0,"mSpeed":0.0,"mStartTime":1711311600000,"mStepCount":0,"mTimeUnit":600000,"mTotalActiveTime":0.0,"mWalkStepCount":0},{"mCalorie":0.0,"mDistance":0.0,"mNowHealthyStep":0,"mRunStepCount":0,"mSpeed":0.0,"mStartTime":1711312200000,"mStepCount":0,"mTimeUnit":600000,"mTotalActiveTime":0.0,"mWalkStepCount":0},{"mCalorie":0.0,"mDistance":0.0,"mNowHealthyStep":0,"mRunStepCount":0,"mSpeed":0.0,"mStartTime":1711312800000,"mStepCount":0,"mTimeUnit":600000,"mTotalActiveTime":0.0,"mWalkStepCount":0},{"mCalorie":0.0,"mDistance":0.0,"mNowHealthyStep":0,"mRunStepCount":0,"mSpeed":0.0,"mStartTime":1711313400000,"mStepCount":0,"mTimeUnit":600000,"mTotalActiveTime":0.0,"mWalkStepCount":0},{"mCalorie":0.0,"mDistance":0.0,"mNowHealthyStep":0,"mRunStepCount":0,"mSpeed":0.0,"mStartTime":1711314000000,"mStepCount":0,"mTimeUnit":600000,"mTotalActiveTime":0.0,"mWalkStepCount":0},{"mCalorie":0.0,"mDistance":0.0,"mNowHealthyStep":0,"mRunStepCount":0,"mSpeed":0.0,"mStartTime":1711314600000,"mStepCount":0,"mTimeUnit":600000,"mTotalActiveTime":0.0,"mWalkStepCount":0},{"mCalorie":0.0,"mDistance":0.0,"mNowHealthyStep":0,"mRunStepCount":0,"mSpeed":0.0,"mStartTime":1711315200000,"mStepCount":0,"mTimeUnit":600000,"mTotalActiveTime":0.0,"mWalkStepCount":0},{"mCalorie":0.0,"mDistance":0.0,"mNowHealthyStep":0,"mRunStepCount":0,"mSpeed":0.0,"mStartTime":1711315800000,"mStepCount":0,"mTimeUnit":600000,"mTotalActiveTime":0.0,"mWalkStepCount":0},{"mCalorie":0.0,"mDistance":0.0,"mNowHealthyStep":0,"mRunStepCount":0,"mSpeed":0.0,"mStartTime":1711316400000,"mStepCount":0,"mTimeUnit":600000,"mTotalActiveTime":0.0,"mWalkStepCount":0},{"mCalorie":0.0,"mDistance":0.0,"mNowHealthyStep":0,"mRunStepCount":0,"mSpeed":0.0,"mStartTime":1711317000000,"mStepCount":0,"mTimeUnit":600000,"mTotalActiveTime":0.0,"mWalkStepCount":0},{"mCalorie":0.0,"mDistance":0.0,"mNowHealthyStep":0,"mRunStepCount":0,"mSpeed":0.0,"mStartTime":1711317600000,"mStepCount":0,"mTimeUnit":600000,"mTotalActiveTime":0.0,"mWalkStepCount":0},{"mCalorie":0.0,"mDistance":0.0,"mNowHealthyStep":0,"mRunStepCount":0,"mSpeed":0.0,"mStartTime":1711318200000,"mStepCount":0,"mTimeUnit":600000,"mTotalActiveTime":0.0,"mWalkStepCount":0},{"mCalorie":0.0,"mDistance":0.0,"mNowHealthyStep":0,"mRunStepCount":0,"mSpeed":0.0,"mStartTime":1711318800000,"mStepCount":0,"mTimeUnit":600000,"mTotalActiveTime":0.0,"mWalkStepCount":0},{"mCalorie":0.0,"mDistance":0.0,"mNowHealthyStep":0,"mRunStepCount":0,"mSpeed":0.0,"mStartTime":1711319400000,"mStepCount":0,"mTimeUnit":600000,"mTotalActiveTime":0.0,"mWalkStepCount":0},{"mCalorie":0.0,"mDistance":0.0,"mNowHealthyStep":0,"mRunStepCount":0,"mSpeed":0.0,"mStartTime":1711320000000,"mStepCount":0,"mTimeUnit":600000,"mTotalActiveTime":0.0,"mWalkStepCount":0},{"mCalorie":0.0,"mDistance":0.0,"mNowHealthyStep":0,"mRunStepCount":0,"mSpeed":0.0,"mStartTime":1711320600000,"mStepCount":0,"mTimeUnit":600000,"mTotalActiveTime":0.0,"mWalkStepCount":0},{"mCalorie":0.0,"mDistance":0.0,"mNowHealthyStep":0,"mRunStepCount":0,"mSpeed":0.0,"mStartTime":1711321200000,"mStepCount":0,"mTimeUnit":600000,"mTotalActiveTime":0.0,"mWalkStepCount":0},{"mCalorie":0.0,"mDistance":0.0,"mNowHealthyStep":0,"mRunStepCount":0,"mSpeed":0.0,"mStartTime":1711321800000,"mStepCount":0,"mTimeUnit":600000,"mTotalActiveTime":0.0,"mWalkStepCount":0},{"mCalorie":0.0,"mDistance":0.0,"mNowHealthyStep":0,"mRunStepCount":0,"mSpeed":0.0,"mStartTime":1711322400000,"mStepCount":0,"mTimeUnit":600000,"mTotalActiveTime":0.0,"mWalkStepCount":0},{"mCalorie":0.0,"mDistance":0.0,"mNowHealthyStep":0,"mRunStepCount":0,"mSpeed":0.0,"mStartTime":1711323000000,"mStepCount":0,"mTimeUnit":600000,"mTotalActiveTime":0.0,"mWalkStepCount":0},{"mCalorie":0.0,"mDistance":0.0,"mNowHealthyStep":0,"mRunStepCount":0,"mSpeed":0.0,"mStartTime":1711323600000,"mStepCount":0,"mTimeUnit":600000,"mTotalActiveTime":0.0,"mWalkStepCount":0},{"mCalorie":0.0,"mDistance":0.0,"mNowHealthyStep":0,"mRunStepCount":0,"mSpeed":0.0,"mStartTime":1711324200000,"mStepCount":0,"mTimeUnit":600000,"mTotalActiveTime":0.0,"mWalkStepCount":0},{"mCalorie":0.0,"mDistance":0.0,"mNowHealthyStep":0,"mRunStepCount":0,"mSpeed":0.0,"mStartTime":1711324800000,"mStepCount":0,"mTimeUnit":600000,"mTotalActiveTime":0.0,"mWalkStepCount":0},{"mCalorie":0.0,"mDistance":0.0,"mNowHealthyStep":0,"mRunStepCount":0,"mSpeed":0.0,"mStartTime":1711325400000,"mStepCount":0,"mTimeUnit":600000,"mTotalActiveTime":0.0,"mWalkStepCount":0},{"mCalorie":0.0,"mDistance":0.0,"mNowHealthyStep":0,"mRunStepCount":0,"mSpeed":0.0,"mStartTime":1711326000000,"mStepCount":0,"mTimeUnit":600000,"mTotalActiveTime":0.0,"mWalkStepCount":0},{"mCalorie":0.0,"mDistance":0.0,"mNowHealthyStep":0,"mRunStepCount":0,"mSpeed":0.0,"mStartTime":1711326600000,"mStepCount":0,"mTimeUnit":600000,"mTotalActiveTime":0.0,"mWalkStepCount":0},{"mCalorie":0.0,"mDistance":0.0,"mNowHealthyStep":0,"mRunStepCount":0,"mSpeed":0.0,"mStartTime":1711327200000,"mStepCount":0,"mTimeUnit":600000,"mTotalActiveTime":0.0,"mWalkStepCount":0},{"mCalorie":0.0,"mDistance":0.0,"mNowHealthyStep":0,"mRunStepCount":0,"mSpeed":0.0,"mStartTime":1711327800000,"mStepCount":0,"mTimeUnit":600000,"mTotalActiveTime":0.0,"mWalkStepCount":0},{"mCalorie":0.0,"mDistance":0.0,"mNowHealthyStep":0,"mRunStepCount":0,"mSpeed":0.0,"mStartTime":1711328400000,"mStepCount":0,"mTimeUnit":600000,"mTotalActiveTime":0.0,"mWalkStepCount":0},{"mCalorie":0.0,"mDistance":0.0,"mNowHealthyStep":0,"mRunStepCount":0,"mSpeed":0.0,"mStartTime":1711329000000,"mStepCount":0,"mTimeUnit":600000,"mTotalActiveTime":0.0,"mWalkStepCount":0},{"mCalorie":0.0,"mDistance":0.0,"mNowHealthyStep":0,"mRunStepCount":0,"mSpeed":0.0,"mStartTime":1711329600000,"mStepCount":0,"mTimeUnit":600000,"mTotalActiveTime":0.0,"mWalkStepCount":0},{"mCalorie":0.0,"mDistance":0.0,"mNowHealthyStep":0,"mRunStepCount":0,"mSpeed":0.0,"mStartTime":1711330200000,"mStepCount":0,"mTimeUnit":600000,"mTotalActiveTime":0.0,"mWalkStepCount":0},{"mCalorie":0.0,"mDistance":0.0,"mNowHealthyStep":0,"mRunStepCount":0,"mSpeed":0.0,"mStartTime":1711330800000,"mStepCount":0,"mTimeUnit":600000,"mTotalActiveTime":0.0,"mWalkStepCount":0},{"mCalorie":0.0,"mDistance":0.0,"mNowHealthyStep":0,"mRunStepCount":0,"mSpeed":0.0,"mStartTime":1711331400000,"mStepCount":0,"mTimeUnit":600000,"mTotalActiveTime":0.0,"mWalkStepCount":0},{"mCalorie":0.0,"mDistance":0.0,"mNowHealthyStep":0,"mRunStepCount":0,"mSpeed":0.0,"mStartTime":1711332000000,"mStepCount":0,"mTimeUnit":600000,"mTotalActiveTime":0.0,"mWalkStepCount":0},{"mCalorie":0.0,"mDistance":0.0,"mNowHealthyStep":0,"mRunStepCount":0,"mSpeed":0.0,"mStartTime":1711332600000,"mStepCount":0,"mTimeUnit":600000,"mTotalActiveTime":0.0,"mWalkStepCount":0},{"mCalorie":0.0,"mDistance":0.0,"mNowHealthyStep":0,"mRunStepCount":0,"mSpeed":0.0,"mStartTime":1711333200000,"mStepCount":0,"mTimeUnit":600000,"mTotalActiveTime":0.0,"mWalkStepCount":0},{"mCalorie":0.0,"mDistance":0.0,"mNowHealthyStep":0,"mRunStepCount":0,"mSpeed":0.0,"mStartTime":1711333800000,"mStepCount":0,"mTimeUnit":600000,"mTotalActiveTime":0.0,"mWalkStepCount":0},{"mCalorie":0.0,"mDistance":0.0,"mNowHealthyStep":0,"mRunStepCount":0,"mSpeed":0.0,"mStartTime":1711334400000,"mStepCount":0,"mTimeUnit":600000,"mTotalActiveTime":0.0,"mWalkStepCount":0},{"mCalorie":0.0,"mDistance":0.0,"mNowHealthyStep":0,"mRunStepCount":0,"mSpeed":0.0,"mStartTime":1711335000000,"mStepCount":0,"mTimeUnit":600000,"mTotalActiveTime":0.0,"mWalkStepCount":0}]