[{"end_time":1671480839000,"heart_rate":82,"heart_rate_max":85,"heart_rate_min":77,"start_time":1671480780000},{"end_time":1671480899000,"heart_rate":97,"heart_rate_max":102,"heart_rate_min":84,"start_time":1671480840000},{"end_time":1671480959000,"heart_rate":103,"heart_rate_max":108,"heart_rate_min":100,"start_time":1671480900000},{"end_time":1671481019000,"heart_rate":101,"heart_rate_max":107,"heart_rate_min":95,"start_time":1671480960000},{"end_time":1671481019000,"heart_rate":97,"heart_rate_max":97,"heart_rate_min":97,"start_time":1671480960000},{"end_time":1671481079000,"heart_rate":102,"heart_rate_max":105,"heart_rate_min":96,"start_time":1671481020000},{"end_time":1671481139000,"heart_rate":102,"heart_rate_max":105,"heart_rate_min":100,"start_time":1671481080000},{"end_time":1671481199000,"heart_rate":105,"heart_rate_max":110,"heart_rate_min":102,"start_time":1671481140000},{"end_time":1671481259000,"heart_rate":106,"heart_rate_max":110,"heart_rate_min":106,"start_time":1671481200000},{"end_time":1671481319000,"heart_rate":104,"heart_rate_max":109,"heart_rate_min":101,"start_time":1671481260000},{"end_time":1671481379000,"heart_rate":110,"heart_rate_max":120,"heart_rate_min":100,"start_time":1671481320000},{"end_time":1671481439000,"heart_rate":110,"heart_rate_max":113,"heart_rate_min":106,"start_time":1671481380000},{"end_time":1671481499000,"heart_rate":107,"heart_rate_max":110,"heart_rate_min":105,"start_time":1671481440000},{"end_time":1671481499000,"heart_rate":109,"heart_rate_max":109,"heart_rate_min":109,"start_time":1671481440000},{"end_time":1671481559000,"heart_rate":110,"heart_rate_max":113,"heart_rate_min":107,"start_time":1671481500000},{"end_time":1671481619000,"heart_rate":112,"heart_rate_max":119,"heart_rate_min":107,"start_time":1671481560000},{"end_time":1671481679000,"heart_rate":107,"heart_rate_max":110,"heart_rate_min":102,"start_time":1671481620000},{"end_time":1671481739000,"heart_rate":104,"heart_rate_max":107,"heart_rate_min":102,"start_time":1671481680000},{"end_time":1671481799000,"heart_rate":109,"heart_rate_max":116,"heart_rate_min":107,"start_time":1671481740000},{"end_time":1671481859000,"heart_rate":104,"heart_rate_max":115,"heart_rate_min":97,"start_time":1671481800000},{"end_time":1671481919000,"heart_rate":100,"heart_rate_max":104,"heart_rate_min":97,"start_time":1671481860000},{"end_time":1671481979000,"heart_rate":110,"heart_rate_max":119,"heart_rate_min":102,"start_time":1671481920000},{"end_time":1671482039000,"heart_rate":115,"heart_rate_max":126,"heart_rate_min":102,"start_time":1671481980000},{"end_time":1671482099000,"heart_rate":104,"heart_rate_max":109,"heart_rate_min":99,"start_time":1671482040000},{"end_time":1671482159000,"heart_rate":104,"heart_rate_max":107,"heart_rate_min":102,"start_time":1671482100000},{"end_time":1671482219000,"heart_rate":105,"heart_rate_max":107,"heart_rate_min":103,"start_time":1671482160000},{"end_time":1671482279000,"heart_rate":106,"heart_rate_max":108,"heart_rate_min":103,"start_time":1671482220000}]