[{"end_time":1632952859000,"heart_rate":101,"heart_rate_max":105,"heart_rate_min":100,"start_time":1632952800000},{"end_time":1632952919000,"heart_rate":104,"heart_rate_max":107,"heart_rate_min":102,"start_time":1632952860000},{"end_time":1632952979000,"heart_rate":99,"heart_rate_max":104,"heart_rate_min":98,"start_time":1632952920000},{"end_time":1632953039000,"heart_rate":95,"heart_rate_max":101,"heart_rate_min":91,"start_time":1632952980000},{"end_time":1632953099000,"heart_rate":101,"heart_rate_max":104,"heart_rate_min":93,"start_time":1632953040000},{"end_time":1632953159000,"heart_rate":104,"heart_rate_max":109,"heart_rate_min":101,"start_time":1632953100000},{"end_time":1632953159000,"heart_rate":106,"heart_rate_max":106,"heart_rate_min":106,"start_time":1632953100000},{"end_time":1632953219000,"heart_rate":100,"heart_rate_max":107,"heart_rate_min":97,"start_time":1632953160000},{"end_time":1632953279000,"heart_rate":102,"heart_rate_max":105,"heart_rate_min":100,"start_time":1632953220000},{"end_time":1632953339000,"heart_rate":103,"heart_rate_max":105,"heart_rate_min":100,"start_time":1632953280000},{"end_time":1632953399000,"heart_rate":105,"heart_rate_max":109,"heart_rate_min":103,"start_time":1632953340000},{"end_time":1632953459000,"heart_rate":107,"heart_rate_max":111,"heart_rate_min":105,"start_time":1632953400000},{"end_time":1632953519000,"heart_rate":114,"heart_rate_max":118,"heart_rate_min":111,"start_time":1632953460000},{"end_time":1632953579000,"heart_rate":110,"heart_rate_max":116,"heart_rate_min":105,"start_time":1632953520000},{"end_time":1632953639000,"heart_rate":106,"heart_rate_max":110,"heart_rate_min":103,"start_time":1632953580000},{"end_time":1632953699000,"heart_rate":102,"heart_rate_max":107,"heart_rate_min":99,"start_time":1632953640000},{"end_time":1632953759000,"heart_rate":97,"heart_rate_max":101,"heart_rate_min":96,"start_time":1632953700000},{"end_time":1632953819000,"heart_rate":99,"heart_rate_max":106,"heart_rate_min":96,"start_time":1632953760000},{"end_time":1632953879000,"heart_rate":104,"heart_rate_max":109,"heart_rate_min":103,"start_time":1632953820000},{"end_time":1632953939000,"heart_rate":101,"heart_rate_max":109,"heart_rate_min":97,"start_time":1632953880000},{"end_time":1632953999000,"heart_rate":101,"heart_rate_max":105,"heart_rate_min":99,"start_time":1632953940000},{"end_time":1632954059000,"heart_rate":108,"heart_rate_max":112,"heart_rate_min":103,"start_time":1632954000000},{"end_time":1632954119000,"heart_rate":105,"heart_rate_max":108,"heart_rate_min":99,"start_time":1632954060000},{"end_time":1632954119000,"heart_rate":99,"heart_rate_max":99,"heart_rate_min":99,"start_time":1632954060000},{"end_time":1632954179000,"heart_rate":100,"heart_rate_max":104,"heart_rate_min":97,"start_time":1632954120000},{"end_time":1632954239000,"heart_rate":104,"heart_rate_max":109,"heart_rate_min":97,"start_time":1632954180000},{"end_time":1632954299000,"heart_rate":105,"heart_rate_max":110,"heart_rate_min":100,"start_time":1632954240000},{"end_time":1632954359000,"heart_rate":100,"heart_rate_max":104,"heart_rate_min":97,"start_time":1632954300000},{"end_time":1632954419000,"heart_rate":104,"heart_rate_max":108,"heart_rate_min":102,"start_time":1632954360000},{"end_time":1632954479000,"heart_rate":103,"heart_rate_max":106,"heart_rate_min":102,"start_time":1632954420000},{"end_time":1632954539000,"heart_rate":112,"heart_rate_max":121,"heart_rate_min":105,"start_time":1632954480000},{"end_time":1632954599000,"heart_rate":112,"heart_rate_max":121,"heart_rate_min":105,"start_time":1632954540000},{"end_time":1632954659000,"heart_rate":99,"heart_rate_max":105,"heart_rate_min":94,"start_time":1632954600000},{"end_time":1632954719000,"heart_rate":100,"heart_rate_max":103,"heart_rate_min":99,"start_time":1632954660000},{"end_time":1632954779000,"heart_rate":99,"heart_rate_max":107,"heart_rate_min":94,"start_time":1632954720000},{"end_time":1632954839000,"heart_rate":98,"heart_rate_max":101,"heart_rate_min":97,"start_time":1632954780000},{"end_time":1632954899000,"heart_rate":99,"heart_rate_max":104,"heart_rate_min":97,"start_time":1632954840000},{"end_time":1632954959000,"heart_rate":102,"heart_rate_max":105,"heart_rate_min":100,"start_time":1632954900000},{"end_time":1632955019000,"heart_rate":95,"heart_rate_max":99,"heart_rate_min":92,"start_time":1632954960000},{"end_time":1632955079000,"heart_rate":97,"heart_rate_max":101,"heart_rate_min":94,"start_time":1632955020000},{"end_time":1632955139000,"heart_rate":100,"heart_rate_max":104,"heart_rate_min":97,"start_time":1632955080000},{"end_time":1632955199000,"heart_rate":95,"heart_rate_max":100,"heart_rate_min":94,"start_time":1632955140000},{"end_time":1632955259000,"heart_rate":96,"heart_rate_max":99,"heart_rate_min":94,"start_time":1632955200000},{"end_time":1632955319000,"heart_rate":98,"heart_rate_max":103,"heart_rate_min":91,"start_time":1632955260000},{"end_time":1632955379000,"heart_rate":103,"heart_rate_max":109,"heart_rate_min":96,"start_time":1632955320000},{"end_time":1632955439000,"heart_rate":105,"heart_rate_max":108,"heart_rate_min":101,"start_time":1632955380000},{"end_time":1632955499000,"heart_rate":115,"heart_rate_max":131,"heart_rate_min":100,"start_time":1632955440000},{"end_time":1632955559000,"heart_rate":126,"heart_rate_max":132,"heart_rate_min":122,"start_time":1632955500000},{"end_time":1632955619000,"heart_rate":126,"heart_rate_max":129,"heart_rate_min":123,"start_time":1632955560000},{"end_time":1632955679000,"heart_rate":121,"heart_rate_max":125,"heart_rate_min":118,"start_time":1632955620000}]